Workbook

Sheet DDM
B1: Dividend Discount Model (DDM)
B2: Abbvie Inc. (ABBV)
B3: Year | C3: Quartely Dividend | D3: Annual Dividend | E3: Growth
B4: 2025 | C4: 1.64 | D4: =C4*4 -> 6.56 | E4: =(D4-D5)/D5 -> 0.058064516
B5: 2024 | C5: 1.55 | D5: =C5*4 -> 6.2 | E5: =(D5-D6)/D6 -> 0.047297297
B6: 2023 | C6: 1.48 | D6: =C6*4 -> 5.92 | E6: =(D6-D7)/D7 -> 0.04964539
B7: 2022 | C7: 1.41 | D7: =C7*4 -> 5.64 | E7: =(D7-D8)/D8 -> 0.084615385
B8: 2021 | C8: 1.3 | D8: =C8*4 -> 5.2 | E8: =(D8-D9)/D9 -> 0.10169492
B9: 2020 | C9: 1.18 | D9: =C9*4 -> 4.72 | E9: =(D9-D10)/D10 -> 0.10280374
B10: 2019 | C10: 1.07 | D10: =C10*4 -> 4.28 | E10: =(D10-D11)/D11 -> 0.19220056
B11: 2018 | C11: 0.96 | D11: =C11*3 + 0.71 -> 3.59 | E11: =(D11-D12)/D12 -> 0.40234375
B12: 2017 | C12: 0.64 | D12: =C12*4 -> 2.56 | E12: =(D12-D13)/D13 -> 0.12280702
B13: 2016 | C13: 0.57 | D13: =C13*4 -> 2.28 | E13: N/A | G13: Required Return (R) Solver
B15: Dividend Growth (g) | D15: =GEOMEAN(E4:E12) -> 0.10151985 | G15: Dividend Growth (g) | I15: =D15 -> 0.10151985
B16: Required Return (r) | D16: =(D4*(1-D15)/D18)+D15 -> 0.1268509 | G16: Required Return (r) | I16: 0.13156
B18: Current Price | D18: 232.68 | G18: Current Price | I18: 218.3
B19: DDM Price | D19: =D4/(D16-D15) -> 258.97066 | G19: DDM Price | I19: =D4/(I16-I15) -> 218.37439
B20: Overvalued or Undervalued | D20: =IF(D19>D18, "Undervalued", "Overvalued") -> Undervalued | G20: Overvalued or Undervalued | I20: =IF(I19>I18, "Undervalued", "Overvalued") -> Undervalued

Sheet DCF
B1: Discounted Cash Flow Analysis Model
B2: Abbvie Inc. (ABBV)
B3: Year | C3: 2015 | D3: 2016 | E3: 2017 | F3: 2018 | G3: 2019 | H3: 2020 | I3: 2021 | J3: 2022 | K3: 2023 | L3: 2024
B4: Free Cash Flow | C4: 7003 | D4: 6562 | E4: 9431 | F4: 12789 | G4: 12772 | H4: 16790 | I4: 21990 | J4: 24248 | K4: 22062 | L4: 17832
B5: Growth | C5: N/A | D5: =(D4-C4)/C4 -> -0.062973012 | E5: =(E4-D4)/D4 -> 0.43721426 | F5: =(F4-E4)/E4 -> 0.3560598 | G5: =(G4-F4)/F4 -> -0.0013292673 | H5: =(H4-G4)/G4 -> 0.31459443 | I5: =(I4-H4)/H4 -> 0.30970816 | J5: =(J4-I4)/I4 -> 0.10268304 | K5: =(K4-J4)/J4 -> -0.090151765 | L5: =(L4-K4)/K4 -> -0.19173239
B6: Average Growth Rate: | C6: =AVERAGE(D5:L5) -> 0.13045258
C8: 1 | D8: 2 | E8: 3 | F8: 4 | G8: 5 | H8: 6 | I8: 7 | J8: 8 | K8: 9 | L8: 10
B9: Year | C9: 2026 | D9: 2027 | E9: 2028 | F9: 2029 | G9: 2030 | H9: 2031 | I9: 2032 | J9: 2033 | K9: 2034 | L9: Terminal Value
B10: Future Free Cash Flows | C10: =L4*(1+C6) -> 20158.23 | D10: =C10*(1+$C$6) -> 22787.924 | E10: =D10*(1+$C$6) -> 25760.667 | F10: =E10*(1+$C$6) -> 29121.213 | G10: =F10*(1+$C$6) -> 32920.15 | H10: =G10*(1+$C$6) -> 37214.669 | I10: =H10*(1+$C$6) -> 42069.419 | J10: =I10*(1+$C$6) -> 47557.483 | K10: =J10*(1+$C$6) -> 53761.48 | L10: =K10*(1+C12)/(C13-C12) -> 1001918.5
B11: PV | C11: =C10/(1+$C$13)^C8 -> 18665.028 | D11: =D10/(1+$C$13)^D8 -> 19536.972 | E11: =E10/(1+$C$13)^E8 -> 20449.648 | F11: =F10/(1+$C$13)^F8 -> 21404.961 | G11: =G10/(1+$C$13)^G8 -> 22404.901 | H11: =H10/(1+$C$13)^H8 -> 23451.554 | I11: =I10/(1+$C$13)^I8 -> 24547.102 | J11: =J10/(1+$C$13)^J8 -> 25693.828 | ... L11: =L10/(1+$C$13)^L8 -> 464082.12
B12: Perpetual Growth Rate: | C12: 0.025
B13: Discount Rate: | C13: 0.08
B15: Total FCF | C15: =SUM(C11:L11) -> 667130.24
B16: Cash + Equivalents | C16: 5555
B17: Total Debt | C17: 67144
B18: Equity Value | C18: =C15+C16-C17 -> 605541.24
B19: Shares Outstanding | C19: 1770
B20: Margin of Safety | C20: 0.25
B21: DCF Share Price | C21: =(C18/C19)*(1-C20) -> 256.58527
B23: Current Price | C23: 232.68
B24: Difference | C24: =(C21-C23)/C23 -> 0.10273882

Sheet Multiples
B1: Multiples Valuation Model
B2: Abbvie Inc. (ABBV)
B3: Ticker | C3: Company Name | D3: Stock Price | E3: EPS | F3: P/E Multiple
B4: JNJ | C4: Johnson & Johnson | D4: 193.2 | E4: 10.43 | F4: =D4/E4 -> 18.52349
B5: NVO | C5: Novo Nordisk | D5: 49.15 | E5: 3.28 | F5: =D5/E5 -> 14.984756
B6: PFE | C6: Pfizer Inc. | D6: 25.8 | E6: 1.73 | F6: =D6/E6 -> 14.913295
B7: UHN | C7: UnitedHealth Group Incorporated | D7: 340.02 | E7: 19.3 | F7: =D7/E7 -> 17.617617
B9: Average P/E | C9: =AVERAGE(F4:F7) -> 16.509789
B10: Median P/E | C10: =MEDIAN(F4:F7) -> 16.301186
B12: Ticker | C12: Stock Price | D12: Forward EPS
B13: ABBV | C13: =C10*D13 -> 254.62453 | D13: 15.62

Sheet Graham's Revised
B1: Benjamin Graham's Revised Valuation Model
B2: Abbvie Inc. (ABBV)
B3: Ticker | C3: ABBV
B4: Forward EPS | C4: 15.62
B5: P/E Constant | C5: 7
B6: Est. EPS Growth Rate | C6: 12.5
B7: Growth Constant | C7: 1
B8: Average Yield of AAA Corp Bonds Constant | C8: 4.4
B9: Current Yield of AAA Corp Bonds | C9: 5.13
B11: Graham's Intrinsic Value | C11: =(C4*(C5+(C7*C6))*C8/C9) -> 261.24678

Sheet Peter Lynch's Adapted FV
B1: Peter Lynch's Adapted FV
B2: Abbvie Inc. (ABBV)
B3: Ticker | C3: ABBV
B4: Forward EPS | C4: 15
B5: Forward P/E | C5: 16.67
B6: PEG | C6: =C5/C7 -> 1.168185
B7: Projected EPS Growth Rate | C7: 14.27
B8: Current Price | C8: 232.68
B10: Fair Value | C10: =C6*C7*C4 -> 250.05

Sheet Final Valuation Analysis
B1: Final Valuation Analysis
B2: Abbvie Inc. (ABBV)
B3: DDM | C3: =DDM!D19 -> 258.97066
B4: DCF | C4: =DCF!C21 -> 256.58527
B5: Multiples | C5: =Multiples!C13 -> 254.62453
B6: Graham's Revised | C6: ='Graham''s Revised'!C11 -> 261.24678
B7: Peter Lynch's Adapted FV | C7: ='Peter Lynch''s Adapted FV'!C10 -> 250.05
B9: Average Fair Value | C9: =AVERAGE(C3:C7) -> 256.29545
B11: Current Price | C11: 232.68
B12: Difference | C12: =(C11/C9)-1 -> -0.092141508
B13: MoS | C13: 0.1
B14: Limit Buy Price | C14: =(1-C13)*C9 -> 230.6659
